django_postgresql_light_schemas/__init__.py
django_postgresql_light_schemas/engine/__init__.py
django_postgresql_light_schemas/engine/base.py
django_postgresql_light_schemas/engine/introspection.py
django_postgresql_light_schemas/engine/schema.py
django_postgresql_light_schemas-0.2.1.dist-info/DESCRIPTION.rst
django_postgresql_light_schemas-0.2.1.dist-info/METADATA
django_postgresql_light_schemas-0.2.1.dist-info/RECORD
django_postgresql_light_schemas-0.2.1.dist-info/WHEEL
django_postgresql_light_schemas-0.2.1.dist-info/metadata.json
django_postgresql_light_schemas-0.2.1.dist-info/top_level.txt
