Metadata-Version: 2.0
Name: django-postgresql-light-schemas
Version: 0.2.1
Summary: Some PostgreSQl introspection fixs to support postgreSQL users binded to specific schemas, multiple schemas on same database for various django installations. No full schema support in models declarations(light).
Home-page: https://github.com/regilero/django_postgresql_light_schemas
Author: Régis Leroy
Author-email: regis.leroy@makina-corpus.com
License: MIT
Keywords: django,postgres,postgresql,schemas
Platform: UNKNOWN
Classifier: Development Status :: 3 - Alpha
Classifier: Framework :: Django
Classifier: Framework :: Django :: 1.10
Classifier: Framework :: Django :: 1.11
Classifier: Intended Audience :: Developers
Classifier: License :: OSI Approved :: BSD License
Classifier: Natural Language :: English
Classifier: Operating System :: OS Independent
Classifier: Programming Language :: Python :: 2
Classifier: Programming Language :: Python :: 2.7
Classifier: Programming Language :: Python :: 3
Classifier: Programming Language :: Python :: 3.4
Classifier: Programming Language :: Python :: 3.5
Classifier: Topic :: Database
Classifier: Topic :: Software Development :: Libraries :: Python Modules
